return {
	[0]  = {Mnemonic="MOVE",      Type="iABC"},
	[1]  = {Mnemonic="LOADK",     Type="iABx"},
	[2]  = {Mnemonic="LOADBOOL",  Type="iABC"},
	[3]  = {Mnemonic="LOADNIL",   Type="iABC"},
	[4]  = {Mnemonic="GETUPVAL",  Type="iABC"},
	[5]  = {Mnemonic="GETGLOBAL", Type="iABx"},
	[6]  = {Mnemonic="GETTABLE",  Type="iABC"},
	[7]  = {Mnemonic="SETGLOBAL", Type="iABx"},
	[8]  = {Mnemonic="SETUPVAL",  Type="iABC"},
	[9]  = {Mnemonic="SETTABLE",  Type="iABC"},
	[10] = {Mnemonic="NEWTABLE",  Type="iABC"},
	[11] = {Mnemonic="SELF",      Type="iABC"},
	[12] = {Mnemonic="ADD",       Type="iABC"},
	[13] = {Mnemonic="SUB",       Type="iABC"},
	[14] = {Mnemonic="MUL",       Type="iABC"},
	[15] = {Mnemonic="DIV",       Type="iABC"},
	[16] = {Mnemonic="MOD",       Type="iABC"},
	[17] = {Mnemonic="POW",       Type="iABC"},
	[18] = {Mnemonic="UNM",       Type="iABC"},
	[19] = {Mnemonic="NOT",       Type="iABC"},
	[20] = {Mnemonic="LEN",       Type="iABC"},
	[21] = {Mnemonic="CONCAT",    Type="iABC"},
	[22] = {Mnemonic="JMP",       Type="iAsBx"},
	[23] = {Mnemonic="EQ",        Type="iABC"},
	[24] = {Mnemonic="LT",        Type="iABC"},
	[25] = {Mnemonic="LE",        Type="iABC"},
	[26] = {Mnemonic="TEST",      Type="iABC"},
	[27] = {Mnemonic="TESTSET",   Type="iABC"},
	[28] = {Mnemonic="CALL",      Type="iABC"},
	[29] = {Mnemonic="TAILCALL",  Type="iABC"},
	[30] = {Mnemonic="RETURN",    Type="iABC"},
	[31] = {Mnemonic="FORLOOP",   Type="iAsBx"},
	[32] = {Mnemonic="FORPREP",   Type="iAsBx"},
	[33] = {Mnemonic="TFORLOOP",  Type="iABC"},
	[34] = {Mnemonic="SETLIST",   Type="iABC"},
	[35] = {Mnemonic="CLOSE",     Type="iABC"},
	[36] = {Mnemonic="CLOSURE",   Type="iABx"},
	[37] = {Mnemonic="VARARG",    Type="iABC"},
}
